tabsdata_mongodb-1.5.0.data/purelib/tabsdata_mongodb/__init__.py
tabsdata_mongodb-1.5.0.data/purelib/tabsdata_mongodb/_connector.py
tabsdata_mongodb-1.5.0.data/purelib/tabsdata_mongodb/assets/manifest/BANNER
tabsdata_mongodb-1.5.0.data/purelib/tabsdata_mongodb/assets/manifest/LICENSE
tabsdata_mongodb-1.5.0.data/purelib/tabsdata_mongodb/assets/manifest/README-PyPi.md
tabsdata_mongodb-1.5.0.data/purelib/tabsdata_mongodb/assets/manifest/RELEASE-NOTES
tabsdata_mongodb-1.5.0.data/purelib/tabsdata_mongodb/assets/manifest/SOURCETRACK.yaml
tabsdata_mongodb-1.5.0.data/purelib/tabsdata_mongodb/assets/manifest/THIRD-PARTY
tabsdata_mongodb-1.5.0.data/purelib/tabsdata_mongodb/assets/manifest/VERSION
tabsdata_mongodb-1.5.0.dist-info/licenses/tabsdata_mongodb/assets/manifest/LICENSE
tabsdata_mongodb-1.5.0.dist-info/METADATA
tabsdata_mongodb-1.5.0.dist-info/WHEEL
tabsdata_mongodb-1.5.0.dist-info/top_level.txt
tabsdata_mongodb-1.5.0.dist-info/RECORD
