Metadata-Version: 2.4
Name: tabsdata_mongodb
Version: 1.5.0
Summary: Tabsdata plugin to access MongoDB data.
Home-page: https://tabsdata.com
Author: Tabs Data Inc.
Project-URL: Source, https://github.com/tabsdata/tabsdata
Requires-Python: >=3.12
License-File: tabsdata_mongodb/assets/manifest/LICENSE
Provides-Extra: deps
Requires-Dist: pymongo==4.15.3; extra == "deps"
Dynamic: author
Dynamic: description
Dynamic: description-content-type
Dynamic: home-page
Dynamic: license-file
Dynamic: project-url
Dynamic: provides-extra
Dynamic: requires-python
Dynamic: summary
